{
  "style": "0",
  "headings": [
    [
      {
        "from": 1,
        "to": 23,
        "mandatory": true
      }
    ]
  ],
  "contents": [
    {
      "from": 1,
      "to": 1662,
      "mandatory": true
    }
  ],
  "children": [
    {
      "style": "1",
      "headings": [
        [
          {
            "from": 553,
            "to": 569,
            "mandatory": true
          }
        ]
      ],
      "contents": [
        {
          "from": 553,
          "to": 1171,
          "mandatory": true
        }
      ],
      "children": [

      ]
    },
    {
      "style": "1",
      "headings": [
        [
          {
            "from": 1172,
            "to": 1205,
            "mandatory": true
          }
        ]
      ],
      "contents": [
        {
          "from": 1172,
          "to": 1662,
          "mandatory": true
        }
      ],
      "children": [

      ]
    }
  ]
}
