{
  "style": "0",
  "headings": [

  ],
  "contents": [
    {
      "from": 1,
      "to": 548,
      "mandatory": true
    }
  ],
  "children": [
    {
      "style": "1",
      "headings": [
        [
          {
            "from": 1,
            "to": 5,
            "mandatory": true
          }
        ]
      ],
      "contents": [
        {
          "from": 1,
          "to": 393,
          "mandatory": true
        }
      ],
      "children": [

      ]
    },
    {
      "style": "1",
      "headings": [
        [
          {
            "from": 406,
            "to": 411,
            "mandatory": true
          }
        ]
      ],
      "contents": [
        {
          "from": 406,
          "to": 548,
          "mandatory": true
        }
      ],
      "children": [

      ]
    }
  ]
}
