{
  "style": "0",
  "headings": [
    [
      {
        "from": 1,
        "to": 50,
        "mandatory": true
      }
    ]
  ],
  "contents": [
    {
      "from": 1,
      "to": 2965,
      "mandatory": true
    }
  ],
  "children": [
    {
      "style": "1",
      "headings": [
        [
          {
            "from": 1310,
            "to": 1351,
            "mandatory": true
          }
        ]
      ],
      "contents": [
        {
          "from": 1310,
          "to": 1926,
          "mandatory": true
        }
      ],
      "children": [

      ]
    }
  ]
}
