{
  "style": "0",
  "headings": [
    [
      {
        "from": 1,
        "to": 18,
        "mandatory": true
      }
    ]
  ],
  "contents": [
    {
      "from": 1,
      "to": 6373,
      "mandatory": true
    }
  ],
  "children": [
    {
      "style": "1",
      "headings": [
        [
          {
            "from": 25,
            "to": 42,
            "mandatory": true
          }
        ]
      ],
      "contents": [
        {
          "from": 25,
          "to": 50,
          "mandatory": true
        }
      ],
      "children": [

      ]
    },
    {
      "style": "2",
      "headings": [
        [
          {
            "from": 230,
            "to": 237,
            "mandatory": true
          }
        ]
      ],
      "contents": [
        {
          "from": 230,
          "to": 555,
          "mandatory": true
        }
      ],
      "children": [

      ]
    },
    {
      "style": "2",
      "headings": [
        [
          {
            "from": 556,
            "to": 563,
            "mandatory": true
          }
        ]
      ],
      "contents": [
        {
          "from": 556,
          "to": 4732,
          "mandatory": true
        }
      ],
      "children": [

      ]
    },
    {
      "style": "2",
      "headings": [
        [
          {
            "from": 4733,
            "to": 4738,
            "mandatory": true
          }
        ]
      ],
      "contents": [
        {
          "from": 4733,
          "to": 6373,
          "mandatory": true
        }
      ],
      "children": [

      ]
    }
  ]
}
