{
  "style": "0",
  "headings": [
    [
      {
        "from": 1,
        "to": 9,
        "mandatory": true
      }
    ]
  ],
  "contents": [
    {
      "from": 1,
      "to": 3359,
      "mandatory": true
    }
  ],
  "children": [
    {
      "style": "1",
      "headings": [
        [
          {
            "from": 2385,
            "to": 2399,
            "mandatory": true
          }
        ]
      ],
      "contents": [
        {
          "from": 2385,
          "to": 2488,
          "mandatory": true
        }
      ],
      "children": [

      ]
    },
    {
      "style": "1",
      "headings": [
        [
          {
            "from": 2489,
            "to": 2513,
            "mandatory": true
          }
        ]
      ],
      "contents": [
        {
          "from": 2489,
          "to": 2752,
          "mandatory": true
        }
      ],
      "children": [

      ]
    },
    {
      "style": "1",
      "headings": [
        [
          {
            "from": 2753,
            "to": 2783,
            "mandatory": true
          }
        ]
      ],
      "contents": [
        {
          "from": 2753,
          "to": 3096,
          "mandatory": true
        }
      ],
      "children": [

      ]
    },
    {
      "style": "2",
      "headings": [
        [
          {
            "from": 3097,
            "to": 3133,
            "mandatory": true
          }
        ]
      ],
      "contents": [
        {
          "from": 3097,
          "to": 3140,
          "mandatory": true
        }
      ],
      "children": [

      ]
    },
    {
      "style": "2",
      "headings": [
        [
          {
            "from": 3141,
            "to": 3181,
            "mandatory": true
          }
        ]
      ],
      "contents": [
        {
          "from": 3141,
          "to": 3302,
          "mandatory": true
        }
      ],
      "children": [

      ]
    }
  ]
}
