{
  "style": "0",
  "headings": [
    [
      {
        "from": 996,
        "to": 1750,
        "mandatory": true
      }
    ]
  ],
  "contents": [
    {
      "from": 1,
      "to": 9330,
      "mandatory": true
    }
  ],
  "children": [
    {
      "style": "3",
      "headings": [
        [
          {
            "from": 3985,
            "to": 4032,
            "mandatory": true
          }
        ]
      ],
      "contents": [
        {
          "from": 3985,
          "to": 9291,
          "mandatory": true
        }
      ],
      "children": [
        {
          "style": "2",
          "headings": [
            [
              {
                "from": 4033,
                "to": 4057,
                "mandatory": true
              }
            ]
          ],
          "contents": [
            {
              "from": 4033,
              "to": 5422,
              "mandatory": true
            }
          ],
          "children": [
            {
              "style": "1",
              "headings": [
                [
                  {
                    "from": 4058,
                    "to": 4099,
                    "mandatory": true
                  }
                ]
              ],
              "contents": [
                {
                  "from": 4058,
                  "to": 4374,
                  "mandatory": true
                }
              ],
              "children": [

              ]
            },
            {
              "style": "1",
              "headings": [
                [
                  {
                    "from": 4375,
                    "to": 4420,
                    "mandatory": true
                  }
                ]
              ],
              "contents": [
                {
                  "from": 4375,
                  "to": 4695,
                  "mandatory": true
                }
              ],
              "children": [

              ]
            },
            {
              "style": "1",
              "headings": [
                [
                  {
                    "from": 4696,
                    "to": 4722,
                    "mandatory": true
                  }
                ]
              ],
              "contents": [
                {
                  "from": 4696,
                  "to": 4997,
                  "mandatory": true
                }
              ],
              "children": [

              ]
            },
            {
              "style": "1",
              "headings": [
                [
                  {
                    "from": 4998,
                    "to": 5028,
                    "mandatory": true
                  }
                ]
              ],
              "contents": [
                {
                  "from": 4998,
                  "to": 5303,
                  "mandatory": true
                }
              ],
              "children": [

              ]
            }
          ]
        },
        {
          "style": "2",
          "headings": [
            [
              {
                "from": 5423,
                "to": 5439,
                "mandatory": true
              }
            ]
          ],
          "contents": [
            {
              "from": 5423,
              "to": 5860,
              "mandatory": true
            }
          ],
          "children": [
            {
              "style": "3",
              "headings": [
                [
                  {
                    "from": 5440,
                    "to": 5466,
                    "mandatory": true
                  }
                ]
              ],
              "contents": [
                {
                  "from": 5440,
                  "to": 5741,
                  "mandatory": true
                }
              ],
              "children": [

              ]
            }
          ]
        },
        {
          "style": "2",
          "headings": [
            [
              {
                "from": 5861,
                "to": 5886,
                "mandatory": true
              }
            ]
          ],
          "contents": [
            {
              "from": 5861,
              "to": 6303,
              "mandatory": true
            }
          ],
          "children": [
            {
              "style": "3",
              "headings": [
                [
                  {
                    "from": 5887,
                    "to": 5909,
                    "mandatory": true
                  }
                ]
              ],
              "contents": [
                {
                  "from": 5887,
                  "to": 6184,
                  "mandatory": true
                }
              ],
              "children": [

              ]
            }
          ]
        },
        {
          "style": "2",
          "headings": [
            [
              {
                "from": 6304,
                "to": 6308,
                "mandatory": true
              }
            ]
          ],
          "contents": [
            {
              "from": 6304,
              "to": 6729,
              "mandatory": true
            }
          ],
          "children": [
            {
              "style": "3",
              "headings": [
                [
                  {
                    "from": 6309,
                    "to": 6335,
                    "mandatory": true
                  }
                ]
              ],
              "contents": [
                {
                  "from": 6309,
                  "to": 6610,
                  "mandatory": true
                }
              ],
              "children": [

              ]
            }
          ]
        },
        {
          "style": "2",
          "headings": [
            [
              {
                "from": 6730,
                "to": 6748,
                "mandatory": true
              }
            ]
          ],
          "contents": [
            {
              "from": 6730,
              "to": 9291,
              "mandatory": true
            }
          ],
          "children": [
            {
              "style": "3",
              "headings": [
                [
                  {
                    "from": 6749,
                    "to": 6775,
                    "mandatory": true
                  }
                ]
              ],
              "contents": [
                {
                  "from": 6749,
                  "to": 7518,
                  "mandatory": true
                }
              ],
              "children": [

              ]
            }
          ]
        }
      ]
    }
  ]
}
