{
  "style": "0",
  "headings": [
    [
      {
        "from": 1,
        "to": 27,
        "mandatory": true
      }
    ]
  ],
  "contents": [
    {
      "from": 1,
      "to": 5882,
      "mandatory": true
    }
  ],
  "children": [
    {
      "style": "1",
      "headings": [
        [
          {
            "from": 47,
            "to": 73,
            "mandatory": true
          }
        ]
      ],
      "contents": [
        {
          "from": 47,
          "to": 375,
          "mandatory": true
        }
      ],
      "children": [

      ]
    },
    {
      "style": "1",
      "headings": [
        [
          {
            "from": 376,
            "to": 409,
            "mandatory": true
          }
        ]
      ],
      "contents": [
        {
          "from": 376,
          "to": 968,
          "mandatory": true
        }
      ],
      "children": [

      ]
    },
    {
      "style": "1",
      "headings": [
        [
          {
            "from": 969,
            "to": 1007,
            "mandatory": true
          }
        ]
      ],
      "contents": [
        {
          "from": 969,
          "to": 1388,
          "mandatory": true
        }
      ],
      "children": [

      ]
    },
    {
      "style": "1",
      "headings": [
        [
          {
            "from": 1389,
            "to": 1423,
            "mandatory": true
          }
        ]
      ],
      "contents": [
        {
          "from": 1389,
          "to": 2506,
          "mandatory": true
        }
      ],
      "children": [

      ]
    },
    {
      "style": "1",
      "headings": [
        [
          {
            "from": 2507,
            "to": 2533,
            "mandatory": true
          }
        ]
      ],
      "contents": [
        {
          "from": 2507,
          "to": 4545,
          "mandatory": true
        }
      ],
      "children": [

      ]
    },
    {
      "style": "1",
      "headings": [
        [
          {
            "from": 4546,
            "to": 4570,
            "mandatory": true
          }
        ]
      ],
      "contents": [
        {
          "from": 4546,
          "to": 5882,
          "mandatory": true
        }
      ],
      "children": [

      ]
    }
  ]
}
