{
  "style": "0",
  "headings": [
    [
      {
        "from": 1,
        "to": 19,
        "mandatory": true
      }
    ]
  ],
  "contents": [
    {
      "from": 1,
      "to": 11421,
      "mandatory": true
    }
  ],
  "children": [
    {
      "style": "1",
      "headings": [
        [
          {
            "from": 631,
            "to": 684,
            "mandatory": true
          }
        ]
      ],
      "contents": [
        {
          "from": 631,
          "to": 2818,
          "mandatory": true
        }
      ],
      "children": [
        {
          "style": "8",
          "headings": [
            [
              {
                "from": 747,
                "to": 769,
                "mandatory": true
              },
              {
                "from": 770,
                "to": 798,
                "mandatory": true
              }
            ]
          ],
          "contents": [
            {
              "from": 747,
              "to": 1022,
              "mandatory": true
            }
          ],
          "children": [

          ]
        },
        {
          "style": "8",
          "headings": [
            [
              {
                "from": 1023,
                "to": 1045,
                "mandatory": true
              },
              {
                "from": 1046,
                "to": 1172,
                "mandatory": true
              }
            ]
          ],
          "contents": [
            {
              "from": 1023,
              "to": 1436,
              "mandatory": true
            }
          ],
          "children": [

          ]
        },
        {
          "style": "8",
          "headings": [
            [
              {
                "from": 1437,
                "to": 1459,
                "mandatory": true
              },
              {
                "from": 1460,
                "to": 1572,
                "mandatory": true
              }
            ]
          ],
          "contents": [
            {
              "from": 1437,
              "to": 1672,
              "mandatory": true
            }
          ],
          "children": [

          ]
        },
        {
          "style": "8",
          "headings": [
            [
              {
                "from": 1673,
                "to": 1695,
                "mandatory": true
              },
              {
                "from": 1696,
                "to": 1826,
                "mandatory": true
              }
            ]
          ],
          "contents": [
            {
              "from": 1673,
              "to": 1911,
              "mandatory": true
            }
          ],
          "children": [

          ]
        },
        {
          "style": "8",
          "headings": [
            [
              {
                "from": 1912,
                "to": 1945,
                "mandatory": true
              },
              {
                "from": 1946,
                "to": 2085,
                "mandatory": true
              }
            ]
          ],
          "contents": [
            {
              "from": 1912,
              "to": 2195,
              "mandatory": true
            }
          ],
          "children": [

          ]
        },
        {
          "style": "8",
          "headings": [
            [
              {
                "from": 2196,
                "to": 2224,
                "mandatory": true
              },
              {
                "from": 2225,
                "to": 2260,
                "mandatory": true
              }
            ]
          ],
          "contents": [
            {
              "from": 2196,
              "to": 2519,
              "mandatory": true
            }
          ],
          "children": [

          ]
        },
        {
          "style": "8",
          "headings": [
            [
              {
                "from": 2520,
                "to": 2542,
                "mandatory": true
              },
              {
                "from": 2543,
                "to": 2685,
                "mandatory": true
              }
            ]
          ],
          "contents": [
            {
              "from": 2520,
              "to": 2818,
              "mandatory": true
            }
          ],
          "children": [

          ]
        }
      ]
    },
    {
      "style": "1",
      "headings": [
        [
          {
            "from": 2819,
            "to": 2858,
            "mandatory": true
          }
        ]
      ],
      "contents": [
        {
          "from": 2819,
          "to": 3535,
          "mandatory": true
        }
      ],
      "children": [
        {
          "style": "7",
          "headings": [
            [
              {
                "from": 2973,
                "to": 2986,
                "mandatory": true
              }
            ]
          ],
          "contents": [
            {
              "from": 2973,
              "to": 3327,
              "mandatory": true
            }
          ],
          "children": [

          ]
        },
        {
          "style": "7",
          "headings": [
            [
              {
                "from": 3328,
                "to": 3344,
                "mandatory": true
              }
            ]
          ],
          "contents": [
            {
              "from": 3328,
              "to": 3535,
              "mandatory": true
            }
          ],
          "children": [

          ]
        }
      ]
    },
    {
      "style": "1",
      "headings": [
        [
          {
            "from": 3536,
            "to": 3562,
            "mandatory": true
          }
        ]
      ],
      "contents": [
        {
          "from": 3536,
          "to": 6222,
          "mandatory": true
        }
      ],
      "children": [
        {
          "style": "6",
          "headings": [
            [
              {
                "from": 3630,
                "to": 3637,
                "mandatory": true
              }
            ]
          ],
          "contents": [
            {
              "from": 3630,
              "to": 3910,
              "mandatory": true
            }
          ],
          "children": [

          ]
        },
        {
          "style": "6",
          "headings": [
            [
              {
                "from": 3911,
                "to": 3922,
                "mandatory": true
              }
            ]
          ],
          "contents": [
            {
              "from": 3911,
              "to": 4109,
              "mandatory": true
            }
          ],
          "children": [

          ]
        },
        {
          "style": "6",
          "headings": [
            [
              {
                "from": 4110,
                "to": 4115,
                "mandatory": true
              }
            ]
          ],
          "contents": [
            {
              "from": 4110,
              "to": 4168,
              "mandatory": true
            }
          ],
          "children": [

          ]
        },
        {
          "style": "6",
          "headings": [
            [
              {
                "from": 4169,
                "to": 4175,
                "mandatory": true
              }
            ]
          ],
          "contents": [
            {
              "from": 4169,
              "to": 4250,
              "mandatory": true
            }
          ],
          "children": [

          ]
        },
        {
          "style": "6",
          "headings": [
            [
              {
                "from": 4251,
                "to": 4258,
                "mandatory": true
              }
            ]
          ],
          "contents": [
            {
              "from": 4251,
              "to": 4438,
              "mandatory": true
            }
          ],
          "children": [

          ]
        }
      ]
    },
    {
      "style": "1",
      "headings": [
        [
          {
            "from": 6223,
            "to": 6254,
            "mandatory": true
          }
        ]
      ],
      "contents": [
        {
          "from": 6223,
          "to": 9074,
          "mandatory": true
        }
      ],
      "children": [
        {
          "style": "5",
          "headings": [
            [
              {
                "from": 6255,
                "to": 6279,
                "mandatory": true
              }
            ]
          ],
          "contents": [
            {
              "from": 6255,
              "to": 6373,
              "mandatory": true
            }
          ],
          "children": [

          ]
        },
        {
          "style": "5",
          "headings": [
            [
              {
                "from": 6374,
                "to": 6412,
                "mandatory": true
              }
            ]
          ],
          "contents": [
            {
              "from": 6374,
              "to": 6778,
              "mandatory": true
            }
          ],
          "children": [

          ]
        },
        {
          "style": "5",
          "headings": [
            [
              {
                "from": 6779,
                "to": 6793,
                "mandatory": true
              }
            ]
          ],
          "contents": [
            {
              "from": 6779,
              "to": 7194,
              "mandatory": true
            }
          ],
          "children": [

          ]
        },
        {
          "style": "5",
          "headings": [
            [
              {
                "from": 7195,
                "to": 7211,
                "mandatory": true
              }
            ]
          ],
          "contents": [
            {
              "from": 7195,
              "to": 7622,
              "mandatory": true
            }
          ],
          "children": [

          ]
        },
        {
          "style": "5",
          "headings": [
            [
              {
                "from": 7623,
                "to": 7646,
                "mandatory": true
              }
            ]
          ],
          "contents": [
            {
              "from": 7623,
              "to": 7973,
              "mandatory": true
            }
          ],
          "children": [

          ]
        },
        {
          "style": "5",
          "headings": [
            [
              {
                "from": 7974,
                "to": 8000,
                "mandatory": true
              }
            ]
          ],
          "contents": [
            {
              "from": 7974,
              "to": 8230,
              "mandatory": true
            }
          ],
          "children": [

          ]
        },
        {
          "style": "5",
          "headings": [
            [
              {
                "from": 8231,
                "to": 8245,
                "mandatory": true
              }
            ]
          ],
          "contents": [
            {
              "from": 8231,
              "to": 8477,
              "mandatory": true
            }
          ],
          "children": [

          ]
        },
        {
          "style": "5",
          "headings": [
            [
              {
                "from": 8478,
                "to": 8510,
                "mandatory": true
              }
            ]
          ],
          "contents": [
            {
              "from": 8478,
              "to": 9074,
              "mandatory": true
            }
          ],
          "children": [

          ]
        }
      ]
    },
    {
      "style": "1",
      "headings": [
        [
          {
            "from": 9075,
            "to": 9095,
            "mandatory": true
          }
        ]
      ],
      "contents": [
        {
          "from": 9075,
          "to": 11135,
          "mandatory": true
        }
      ],
      "children": [
        {
          "style": "4",
          "headings": [
            [
              {
                "from": 9151,
                "to": 9177,
                "mandatory": true
              },
              {
                "from": 9178,
                "to": 9221,
                "mandatory": true
              }
            ]
          ],
          "contents": [
            {
              "from": 9151,
              "to": 9532,
              "mandatory": true
            }
          ],
          "children": [

          ]
        },
        {
          "style": "4",
          "headings": [
            [
              {
                "from": 9533,
                "to": 9560,
                "mandatory": true
              },
              {
                "from": 9561,
                "to": 9585,
                "mandatory": true
              }
            ]
          ],
          "contents": [
            {
              "from": 9533,
              "to": 9904,
              "mandatory": true
            }
          ],
          "children": [

          ]
        },
        {
          "style": "4",
          "headings": [
            [
              {
                "from": 9905,
                "to": 9937,
                "mandatory": true
              },
              {
                "from": 9938,
                "to": 9993,
                "mandatory": true
              }
            ]
          ],
          "contents": [
            {
              "from": 9905,
              "to": 10185,
              "mandatory": true
            }
          ],
          "children": [

          ]
        },
        {
          "style": "4",
          "headings": [
            [
              {
                "from": 10186,
                "to": 10219,
                "mandatory": true
              },
              {
                "from": 10220,
                "to": 10252,
                "mandatory": true
              }
            ]
          ],
          "contents": [
            {
              "from": 10186,
              "to": 10506,
              "mandatory": true
            }
          ],
          "children": [

          ]
        },
        {
          "style": "4",
          "headings": [
            [
              {
                "from": 10507,
                "to": 10537,
                "mandatory": true
              },
              {
                "from": 10538,
                "to": 10555,
                "mandatory": true
              }
            ]
          ],
          "contents": [
            {
              "from": 10507,
              "to": 10806,
              "mandatory": true
            }
          ],
          "children": [

          ]
        },
        {
          "style": "4",
          "headings": [
            [
              {
                "from": 10807,
                "to": 10829,
                "mandatory": true
              },
              {
                "from": 10830,
                "to": 10892,
                "mandatory": true
              }
            ]
          ],
          "contents": [
            {
              "from": 10807,
              "to": 11050,
              "mandatory": true
            }
          ],
          "children": [

          ]
        }
      ]
    },
    {
      "style": "2",
      "headings": [
        [
          {
            "from": 11136,
            "to": 11150,
            "mandatory": true
          }
        ]
      ],
      "contents": [
        {
          "from": 11136,
          "to": 11421,
          "mandatory": true
        }
      ],
      "children": [
        {
          "style": "3",
          "headings": [
            [
              {
                "from": 11151,
                "to": 11158,
                "mandatory": true
              }
            ]
          ],
          "contents": [
            {
              "from": 11151,
              "to": 11266,
              "mandatory": true
            }
          ],
          "children": [

          ]
        },
        {
          "style": "3",
          "headings": [
            [
              {
                "from": 11267,
                "to": 11295,
                "mandatory": true
              }
            ]
          ],
          "contents": [
            {
              "from": 11267,
              "to": 11343,
              "mandatory": true
            }
          ],
          "children": [

          ]
        },
        {
          "style": "3",
          "headings": [
            [
              {
                "from": 11344,
                "to": 11359,
                "mandatory": true
              }
            ]
          ],
          "contents": [
            {
              "from": 11344,
              "to": 11421,
              "mandatory": true
            }
          ],
          "children": [

          ]
        }
      ]
    }
  ]
}
