{
  "style": "0",
  "headings": [
    [
      {
        "from": 17,
        "to": 61,
        "mandatory": true
      }
    ]
  ],
  "contents": [
    {
      "from": 1,
      "to": 336,
      "mandatory": true
    }
  ],
  "children": [
    {
      "style": "1",
      "headings": [
        [
          {
            "from": 270,
            "to": 277,
            "mandatory": true
          }
        ]
      ],
      "contents": [
        {
          "from": 270,
          "to": 287,
          "mandatory": true
        }
      ],
      "children": [

      ]
    },
    {
      "style": "1",
      "headings": [
        [
          {
            "from": 288,
            "to": 299,
            "mandatory": true
          }
        ]
      ],
      "contents": [
        {
          "from": 288,
          "to": 313,
          "mandatory": true
        }
      ],
      "children": [

      ]
    },
    {
      "style": "1",
      "headings": [
        [
          {
            "from": 314,
            "to": 324,
            "mandatory": true
          }
        ]
      ],
      "contents": [
        {
          "from": 314,
          "to": 336,
          "mandatory": true
        }
      ],
      "children": [

      ]
    }
  ]
}
